pywhisker/__init__.py
pywhisker/pywhisker.py
pywhisker-0.1.2.dist-info/LICENSE
pywhisker-0.1.2.dist-info/METADATA
pywhisker-0.1.2.dist-info/WHEEL
pywhisker-0.1.2.dist-info/entry_points.txt
pywhisker-0.1.2.dist-info/RECORD
