Metadata-Version: 2.1
Name: pywhisker
Version: 0.1.2
Summary: Unofficial Package for PyWhisker Pentesting Tool
Home-page: https://github.com/ShutdownRepo/pywhisker
License: GPL-3.0
Keywords: pywhisker,pywhisker.py,shadow credentials,ad,active directory,pentesting
Author: Charlie Bromberg and Podalirius of PyWhisker
Maintainer: ReKon64
Requires-Python: >=3.8,<4.0
Classifier: License :: OSI Approved :: GNU General Public License v3 (GPLv3)
Classifier: Programming Language :: Python :: 3
Classifier: Programming Language :: Python :: 3.8
Classifier: Programming Language :: Python :: 3.9
Classifier: Programming Language :: Python :: 3.10
Classifier: Programming Language :: Python :: 3.11
Classifier: Programming Language :: Python :: 3.12
Classifier: Programming Language :: Python :: 3.13
Requires-Dist: dsinternals (==1.2.4)
Requires-Dist: impacket (==0.12.0)
Requires-Dist: ldap3 (==2.9.1)
Requires-Dist: ldapdomaindump (==0.9.4)
Requires-Dist: pyasn1 (==0.6.0)
Requires-Dist: pygments (>=2.13.0,<3.0.0)
Requires-Dist: rich (==13.7.1)
Requires-Dist: six (==1.16.0)
